Metadata-Version: 2.1
Name: Gzmo
Version: 1a2
Summary: Process JSON like data structures using process strings
Home-page: https://bitbucket.org/notequal/gzmo/
Author: Stanley Engle
Author-email: stan.engle@gmail.com
License: BSD License
Classifier: Development Status :: 3 - Alpha
Classifier: Intended Audience :: Developers
Classifier: Intended Audience :: Science/Research
Classifier: License :: OSI Approved :: BSD License
Classifier: Natural Language :: English
Classifier: Operating System :: OS Independent
Classifier: Programming Language :: Python :: 3.10
License-File: LICENSE
